raudhahpay/__init__.py
raudhahpay/raudhahpay.py
raudhahpay-0.0.1.dist-info/LICENSE
raudhahpay-0.0.1.dist-info/METADATA
raudhahpay-0.0.1.dist-info/WHEEL
raudhahpay-0.0.1.dist-info/top_level.txt
raudhahpay-0.0.1.dist-info/RECORD
