Metadata-Version: 2.1
Name: raudhahpay
Version: 0.0.1
Summary: Raudhah Pay Python Simple SDK
Home-page: https://github.com/faridyusof727/raudhahpayapi
Author: Farid Yusof
Author-email: faridyusof727@gmail.com
License: UNKNOWN
Platform: UNKNOWN
Classifier: Programming Language :: Python :: 3
Classifier: License :: OSI Approved :: MIT License
Classifier: Operating System :: OS Independent
Requires-Python: >=3.6
Requires-Dist: requests
